{"ddd":0,"h":1200,"w":1200,"meta":{"g":"@lottiefiles/toolkit-js 0.57.2-beta.0"},"layers":[{"ty":3,"sr":1,"st":0,"op":300,"ip":0,"ln":"5276","hasMask":false,"ao":0,"ks":{"a":{"a":0,"k":[0,0]},"s":{"a":0,"k":[48,48,97.959]},"p":{"a":0,"k":[605.389,611.581,0]},"r":{"a":0,"k":0},"o":{"a":0,"k":100}},"ind":1},{"ty":4,"sr":1,"st":279,"op":321,"ip":275,"ln":"5283","hasMask":false,"ao":0,"ks":{"a":{"a":0,"k":[0,0]},"s":{"a":0,"k":[100,100]},"p":{"a":0,"k":[0,0,0]},"r":{"a":0,"k":180},"o":{"a":0,"k":100}},"shapes":[{"ty":"gr","it":[{"ty":"sh","d":1,"ks":{"a":1,"k":[{"o":{"x":0.16,"y":0},"i":{"x":0.1,"y":1},"s":[{"c":false,"i":[[-0.917,0],[0,-280.285],[286.869,0]],"o":[[286.869,0],[0,280.285],[-0.542,0]],"v":[[0,-507.5],[507.5,0],[0,507.5]]}],"t":275},{"s":[{"c":false,"i":[[-0.917,0],[0,-280.285],[189.474,0]],"o":[[173.684,0],[0,280.285],[-0.542,0]],"v":[[0,-507.5],[507.5,0],[0,507.5]]}],"t":320}]}},{"ty":"tr","a":{"a":0,"k":[0,0]},"s":{"a":1,"k":[{"s":[-100,100],"i":{"x":[0,0.1],"y":[1,1]},"o":{"x":[0.287,0.16],"y":[0,0]},"t":275},{"s":[38,100],"i":{"x":[0.1,0.1],"y":[1,1]},"o":{"x":[0,0],"y":[0,0]},"t":320}]},"p":{"a":0,"k":[0,0]},"r":{"a":0,"k":0},"o":{"a":0,"k":100}}]},{"ty":"st","lc":2,"lj":2,"ml":4,"o":{"a":0,"k":100},"w":{"a":0,"k":108},"c":{"a":0,"k":[1,0.5765,0.251]}}],"ind":2,"parent":1},{"ty":4,"sr":1,"st":295,"op":321,"ip":287,"ln":"5282","hasMask":false,"ao":0,"ks":{"a":{"a":0,"k":[0,0]},"s":{"a":0,"k":[100,100]},"p":{"a":0,"k":[0,0,0]},"r":{"a":0,"k":180},"o":{"a":0,"k":100}},"shapes":[{"ty":"gr","it":[{"ty":"sh","d":1,"ks":{"a":1,"k":[{"o":{"x":0.04,"y":0},"i":{"x":0.35,"y":1},"s":[{"c":false,"i":[[-0.917,0],[0,-280.285],[286.869,0]],"o":[[286.869,0],[0,280.285],[-0.542,0]],"v":[[0,-507.5],[507.5,0],[0,507.5]]}],"t":287},{"s":[{"c":false,"i":[[-0.917,0],[0,-280.285],[189.474,0]],"o":[[173.684,0],[0,280.285],[-0.542,0]],"v":[[0,-507.5],[507.5,0],[0,507.5]]}],"t":320}]}},{"ty":"tr","a":{"a":0,"k":[0,0]},"s":{"a":1,"k":[{"s":[-100,100],"i":{"x":[0.35,0.35],"y":[1,1]},"o":{"x":[0.04,0.04],"y":[0.07,0]},"t":287},{"s":[-39,100],"i":{"x":[0.35,0.35],"y":[1,1]},"o":{"x":[0.167,0.167],"y":[0,0]},"t":320}]},"p":{"a":0,"k":[0,0]},"r":{"a":0,"k":0},"o":{"a":0,"k":100}}]},{"ty":"st","lc":2,"lj":2,"ml":4,"o":{"a":0,"k":100},"w":{"a":0,"k":108},"c":{"a":0,"k":[1,0.5765,0.251]}}],"ind":3,"parent":1},{"ty":4,"sr":1,"st":261,"op":299,"ip":78,"ln":"5280","hasMask":false,"ao":0,"ks":{"a":{"a":0,"k":[0,0]},"s":{"a":0,"k":[100,100]},"p":{"a":0,"k":[0,0,0]},"r":{"a":0,"k":0},"o":{"a":0,"k":100}},"shapes":[{"ty":"gr","it":[{"ty":"sh","d":1,"ks":{"a":0,"k":{"c":false,"i":[[-0.917,0],[0,-280.285],[286.869,0]],"o":[[286.869,0],[0,280.285],[-0.542,0]],"v":[[0,-507.5],[507.5,0],[0,507.5]]}}},{"ty":"tr","a":{"a":0,"k":[0,0]},"s":{"a":1,"k":[{"s":[100,100],"i":{"x":[0.526,0.55],"y":[1,1]},"o":{"x":[0.66,0.66],"y":[0,0]},"t":261},{"s":[-100,100],"i":{"x":[0.55,0.55],"y":[1,1]},"o":{"x":[0.167,0.167],"y":[0,0]},"t":296}]},"p":{"a":0,"k":[0,0]},"r":{"a":0,"k":0},"o":{"a":0,"k":100}}]},{"ty":"st","lc":2,"lj":2,"ml":4,"o":{"a":0,"k":100},"w":{"a":0,"k":108},"c":{"a":0,"k":[1,0.5765,0.251]}}],"ind":4,"parent":1},{"ty":4,"sr":1,"st":261,"op":283,"ip":78,"ln":"5279","hasMask":false,"ao":0,"ks":{"a":{"a":0,"k":[0,0]},"s":{"a":0,"k":[100,100]},"p":{"a":0,"k":[0,0,0]},"r":{"a":0,"k":0},"o":{"a":0,"k":100}},"shapes":[{"ty":"gr","it":[{"ty":"sh","d":1,"ks":{"a":1,"k":[{"o":{"x":0.66,"y":0},"i":{"x":0.93,"y":0.999},"s":[{"c":false,"i":[[-0.917,0],[0,-280.285],[189.474,0]],"o":[[173.684,0],[0,280.285],[-0.542,0]],"v":[[0,-507.5],[507.5,0],[0,507.5]]}],"t":261},{"s":[{"c":false,"i":[[-0.917,0],[0,-280.285],[286.869,0]],"o":[[286.869,0],[0,280.285],[-0.542,0]],"v":[[0,-507.5],[507.5,0],[0,507.5]]}],"t":282}]}},{"ty":"tr","a":{"a":0,"k":[0,0]},"s":{"a":1,"k":[{"s":[38,100],"i":{"x":[0.93,0.93],"y":[0.81,1]},"o":{"x":[0.66,0.66],"y":[0,0]},"t":261},{"s":[-100,100],"i":{"x":[0.93,0.93],"y":[1,1]},"o":{"x":[0.167,0.167],"y":[0,0]},"t":282}]},"p":{"a":0,"k":[0,0]},"r":{"a":0,"k":0},"o":{"a":0,"k":100}}]},{"ty":"st","lc":2,"lj":2,"ml":4,"o":{"a":0,"k":100},"w":{"a":0,"k":108},"c":{"a":0,"k":[1,0.5765,0.251]}}],"ind":5,"parent":1},{"ty":4,"sr":1,"st":261,"op":277,"ip":78,"ln":"5278","hasMask":false,"ao":0,"ks":{"a":{"a":0,"k":[0,0]},"s":{"a":0,"k":[100,100]},"p":{"a":0,"k":[0,0,0]},"r":{"a":0,"k":0},"o":{"a":0,"k":100}},"shapes":[{"ty":"gr","it":[{"ty":"sh","d":1,"ks":{"a":1,"k":[{"o":{"x":0.66,"y":0},"i":{"x":0.94,"y":1},"s":[{"c":false,"i":[[-0.917,0],[0,-280.285],[189.474,0]],"o":[[173.684,0],[0,280.285],[-0.542,0]],"v":[[0,-507.5],[507.5,0],[0,507.5]]}],"t":261},{"s":[{"c":false,"i":[[-0.917,0],[0,-280.285],[286.869,0]],"o":[[286.869,0],[0,280.285],[-0.542,0]],"v":[[0,-507.5],[507.5,0],[0,507.5]]}],"t":277}]}},{"ty":"tr","a":{"a":0,"k":[0,0]},"s":{"a":1,"k":[{"s":[-39,100],"i":{"x":[0.94,0.94],"y":[0.91,1]},"o":{"x":[0.66,0.66],"y":[0,0]},"t":261},{"s":[-100,100],"i":{"x":[0.94,0.94],"y":[1,1]},"o":{"x":[0.167,0.167],"y":[0,0]},"t":277}]},"p":{"a":0,"k":[0,0]},"r":{"a":0,"k":0},"o":{"a":0,"k":100}}]},{"ty":"st","lc":2,"lj":2,"ml":4,"o":{"a":0,"k":100},"w":{"a":0,"k":108},"c":{"a":0,"k":[1,0.5765,0.251]}}],"ind":6,"parent":1},{"ty":4,"sr":1,"st":261,"op":321,"ip":78,"ln":"5277","hasMask":false,"ao":0,"ks":{"a":{"a":0,"k":[0,0]},"s":{"a":0,"k":[100,100]},"p":{"a":0,"k":[0,0,0]},"r":{"a":0,"k":0},"o":{"a":0,"k":100}},"shapes":[{"ty":"gr","it":[{"ty":"el","d":1,"p":{"a":0,"k":[0,0]},"s":{"a":0,"k":[1015,1015]}},{"ty":"sh","d":1,"ks":{"a":0,"k":{"c":false,"i":[[0,0],[0,0]],"o":[[0,0],[0,0]],"v":[[-473,-167],[468,-167]]}}},{"ty":"sh","d":1,"ks":{"a":0,"k":{"c":false,"i":[[0,0],[0,0]],"o":[[0,0],[0,0]],"v":[[-473,168],[468,168]]}}},{"ty":"tr","a":{"a":0,"k":[0,0]},"s":{"a":0,"k":[100,100]},"p":{"a":0,"k":[0,0]},"r":{"a":0,"k":0},"o":{"a":0,"k":100}}]},{"ty":"st","lc":2,"lj":2,"ml":4,"o":{"a":0,"k":100},"w":{"a":0,"k":108},"c":{"a":0,"k":[1,0.5765,0.251]}}],"ind":7,"parent":1},{"ty":4,"sr":1,"st":38,"op":80,"ip":34,"ln":"5275","hasMask":false,"ao":0,"ks":{"a":{"a":0,"k":[0,0]},"s":{"a":0,"k":[100,100]},"p":{"a":0,"k":[0,0,0]},"r":{"a":0,"k":180},"o":{"a":0,"k":100}},"shapes":[{"ty":"gr","it":[{"ty":"sh","d":1,"ks":{"a":1,"k":[{"o":{"x":0.16,"y":0},"i":{"x":0.1,"y":1},"s":[{"c":false,"i":[[-0.917,0],[0,-280.285],[286.869,0]],"o":[[286.869,0],[0,280.285],[-0.542,0]],"v":[[0,-507.5],[507.5,0],[0,507.5]]}],"t":34},{"s":[{"c":false,"i":[[-0.917,0],[0,-280.285],[189.474,0]],"o":[[173.684,0],[0,280.285],[-0.542,0]],"v":[[0,-507.5],[507.5,0],[0,507.5]]}],"t":79}]}},{"ty":"tr","a":{"a":0,"k":[0,0]},"s":{"a":1,"k":[{"s":[-100,100],"i":{"x":[0,0.1],"y":[1,1]},"o":{"x":[0.287,0.16],"y":[0,0]},"t":34},{"s":[38,100],"i":{"x":[0.1,0.1],"y":[1,1]},"o":{"x":[0,0],"y":[0,0]},"t":79}]},"p":{"a":0,"k":[0,0]},"r":{"a":0,"k":0},"o":{"a":0,"k":100}}]},{"ty":"st","lc":2,"lj":2,"ml":4,"o":{"a":0,"k":100},"w":{"a":0,"k":108},"c":{"a":0,"k":[1,0.5765,0.251]}}],"ind":8,"parent":1},{"ty":4,"sr":1,"st":54,"op":80,"ip":46,"ln":"5274","hasMask":false,"ao":0,"ks":{"a":{"a":0,"k":[0,0]},"s":{"a":0,"k":[100,100]},"p":{"a":0,"k":[0,0,0]},"r":{"a":0,"k":180},"o":{"a":0,"k":100}},"shapes":[{"ty":"gr","it":[{"ty":"sh","d":1,"ks":{"a":1,"k":[{"o":{"x":0.04,"y":0},"i":{"x":0.35,"y":1},"s":[{"c":false,"i":[[-0.917,0],[0,-280.285],[286.869,0]],"o":[[286.869,0],[0,280.285],[-0.542,0]],"v":[[0,-507.5],[507.5,0],[0,507.5]]}],"t":46},{"s":[{"c":false,"i":[[-0.917,0],[0,-280.285],[189.474,0]],"o":[[173.684,0],[0,280.285],[-0.542,0]],"v":[[0,-507.5],[507.5,0],[0,507.5]]}],"t":79}]}},{"ty":"tr","a":{"a":0,"k":[0,0]},"s":{"a":1,"k":[{"s":[-100,100],"i":{"x":[0.35,0.35],"y":[1,1]},"o":{"x":[0.04,0.04],"y":[0.07,0]},"t":46},{"s":[-39,100],"i":{"x":[0.35,0.35],"y":[1,1]},"o":{"x":[0.167,0.167],"y":[0,0]},"t":79}]},"p":{"a":0,"k":[0,0]},"r":{"a":0,"k":0},"o":{"a":0,"k":100}}]},{"ty":"st","lc":2,"lj":2,"ml":4,"o":{"a":0,"k":100},"w":{"a":0,"k":108},"c":{"a":0,"k":[1,0.5765,0.251]}}],"ind":9,"parent":1},{"ty":4,"sr":1,"st":20,"op":58,"ip":-1,"ln":"5272","hasMask":false,"ao":0,"ks":{"a":{"a":0,"k":[0,0]},"s":{"a":0,"k":[100,100]},"p":{"a":0,"k":[0,0,0]},"r":{"a":0,"k":0},"o":{"a":0,"k":100}},"shapes":[{"ty":"gr","it":[{"ty":"sh","d":1,"ks":{"a":0,"k":{"c":false,"i":[[-0.917,0],[0,-280.285],[286.869,0]],"o":[[286.869,0],[0,280.285],[-0.542,0]],"v":[[0,-507.5],[507.5,0],[0,507.5]]}}},{"ty":"tr","a":{"a":0,"k":[0,0]},"s":{"a":1,"k":[{"s":[100,100],"i":{"x":[0.526,0.55],"y":[1,1]},"o":{"x":[0.66,0.66],"y":[0,0]},"t":20},{"s":[-100,100],"i":{"x":[0.55,0.55],"y":[1,1]},"o":{"x":[0.167,0.167],"y":[0,0]},"t":55}]},"p":{"a":0,"k":[0,0]},"r":{"a":0,"k":0},"o":{"a":0,"k":100}}]},{"ty":"st","lc":2,"lj":2,"ml":4,"o":{"a":0,"k":100},"w":{"a":0,"k":108},"c":{"a":0,"k":[1,0.5765,0.251]}}],"ind":10,"parent":1},{"ty":4,"sr":1,"st":20,"op":42,"ip":-1,"ln":"5271","hasMask":false,"ao":0,"ks":{"a":{"a":0,"k":[0,0]},"s":{"a":0,"k":[100,100]},"p":{"a":0,"k":[0,0,0]},"r":{"a":0,"k":0},"o":{"a":0,"k":100}},"shapes":[{"ty":"gr","it":[{"ty":"sh","d":1,"ks":{"a":1,"k":[{"o":{"x":0.66,"y":0},"i":{"x":0.93,"y":0.999},"s":[{"c":false,"i":[[-0.917,0],[0,-280.285],[189.474,0]],"o":[[173.684,0],[0,280.285],[-0.542,0]],"v":[[0,-507.5],[507.5,0],[0,507.5]]}],"t":20},{"s":[{"c":false,"i":[[-0.917,0],[0,-280.285],[286.869,0]],"o":[[286.869,0],[0,280.285],[-0.542,0]],"v":[[0,-507.5],[507.5,0],[0,507.5]]}],"t":41}]}},{"ty":"tr","a":{"a":0,"k":[0,0]},"s":{"a":1,"k":[{"s":[38,100],"i":{"x":[0.93,0.93],"y":[0.81,1]},"o":{"x":[0.66,0.66],"y":[0,0]},"t":20},{"s":[-100,100],"i":{"x":[0.93,0.93],"y":[1,1]},"o":{"x":[0.167,0.167],"y":[0,0]},"t":41}]},"p":{"a":0,"k":[0,0]},"r":{"a":0,"k":0},"o":{"a":0,"k":100}}]},{"ty":"st","lc":2,"lj":2,"ml":4,"o":{"a":0,"k":100},"w":{"a":0,"k":108},"c":{"a":0,"k":[1,0.5765,0.251]}}],"ind":11,"parent":1},{"ty":4,"sr":1,"st":20,"op":36,"ip":-1,"ln":"5270","hasMask":false,"ao":0,"ks":{"a":{"a":0,"k":[0,0]},"s":{"a":0,"k":[100,100]},"p":{"a":0,"k":[0,0,0]},"r":{"a":0,"k":0},"o":{"a":0,"k":100}},"shapes":[{"ty":"gr","it":[{"ty":"sh","d":1,"ks":{"a":1,"k":[{"o":{"x":0.66,"y":0},"i":{"x":0.94,"y":1},"s":[{"c":false,"i":[[-0.917,0],[0,-280.285],[189.474,0]],"o":[[173.684,0],[0,280.285],[-0.542,0]],"v":[[0,-507.5],[507.5,0],[0,507.5]]}],"t":20},{"s":[{"c":false,"i":[[-0.917,0],[0,-280.285],[286.869,0]],"o":[[286.869,0],[0,280.285],[-0.542,0]],"v":[[0,-507.5],[507.5,0],[0,507.5]]}],"t":36}]}},{"ty":"tr","a":{"a":0,"k":[0,0]},"s":{"a":1,"k":[{"s":[-39,100],"i":{"x":[0.94,0.94],"y":[0.91,1]},"o":{"x":[0.66,0.66],"y":[0,0]},"t":20},{"s":[-100,100],"i":{"x":[0.94,0.94],"y":[1,1]},"o":{"x":[0.167,0.167],"y":[0,0]},"t":36}]},"p":{"a":0,"k":[0,0]},"r":{"a":0,"k":0},"o":{"a":0,"k":100}}]},{"ty":"st","lc":2,"lj":2,"ml":4,"o":{"a":0,"k":100},"w":{"a":0,"k":108},"c":{"a":0,"k":[1,0.5765,0.251]}}],"ind":12,"parent":1},{"ty":4,"sr":1,"st":20,"op":80,"ip":-1,"ln":"5269","hasMask":false,"ao":0,"ks":{"a":{"a":0,"k":[0,0]},"s":{"a":0,"k":[100,100]},"p":{"a":0,"k":[0,0,0]},"r":{"a":0,"k":0},"o":{"a":0,"k":100}},"shapes":[{"ty":"gr","it":[{"ty":"el","d":1,"p":{"a":0,"k":[0,0]},"s":{"a":0,"k":[1015,1015]}},{"ty":"sh","d":1,"ks":{"a":0,"k":{"c":false,"i":[[0,0],[0,0]],"o":[[0,0],[0,0]],"v":[[-473,-167],[468,-167]]}}},{"ty":"sh","d":1,"ks":{"a":0,"k":{"c":false,"i":[[0,0],[0,0]],"o":[[0,0],[0,0]],"v":[[-473,168],[468,168]]}}},{"ty":"tr","a":{"a":0,"k":[0,0]},"s":{"a":0,"k":[100,100]},"p":{"a":0,"k":[0,0]},"r":{"a":0,"k":0},"o":{"a":0,"k":100}}]},{"ty":"st","lc":2,"lj":2,"ml":4,"o":{"a":0,"k":100},"w":{"a":0,"k":108},"c":{"a":0,"k":[1,0.5765,0.251]}}],"ind":13,"parent":1},{"ty":4,"sr":1,"st":0,"op":1200,"ip":0,"ln":"3467","hasMask":false,"ao":0,"ks":{"a":{"a":0,"k":[0,0]},"s":{"a":0,"k":[100,100]},"p":{"a":0,"k":[600,600]},"r":{"a":0,"k":180},"o":{"a":0,"k":100}},"shapes":[{"ty":"gr","it":[{"ty":"rc","d":1,"p":{"a":0,"k":[0,0]},"r":{"a":0,"k":0},"s":{"a":0,"k":[800,800]}},{"ty":"fl","c":{"a":0,"k":[0.0078,0.0196,0.0392]},"r":1,"o":{"a":0,"k":100}},{"ty":"tr","a":{"a":0,"k":[0,0]},"s":{"a":0,"k":[100,100]},"p":{"a":0,"k":[0,0]},"r":{"a":0,"k":0},"o":{"a":0,"k":100}}]}],"ind":14},{"ty":4,"sr":1,"st":0,"op":1200,"ip":0,"ln":"3439","hasMask":false,"ao":0,"ks":{"a":{"a":0,"k":[0,0]},"s":{"a":0,"k":[100,100]},"p":{"a":0,"k":[600,600]},"r":{"a":0,"k":0},"o":{"a":0,"k":100}},"shapes":[{"ty":"rc","d":1,"p":{"a":0,"k":[0,0]},"r":{"a":0,"k":0},"s":{"a":0,"k":[1200,1200]}},{"ty":"fl","c":{"a":0,"k":[1,0.5765,0.251]},"r":1,"o":{"a":0,"k":100}}],"ind":15}],"v":"5.7.0","fr":60,"op":239,"ip":0,"assets":[]}